{
  "oem":"Nokia",
  "name":"Nokia 8",
  "codename":"NB1",
  "filename":"Havoc-OS-v4.6-20210702-NB1-Official.zip",
  "version":"4.6",
  "romtype":"Official",
  "variant":"Vanilla",
  "maintainer":"Edward Wu (edwardwu0223)",
  "size":721007324,
  "datetime":1625218567,
  "filehash":"4fa7f17c2edfada8aae06806f8236b1f",
  "id":"fb111f4b56dd44f92b79681e960a74ef09464a4a392fa8e4dfbb327261fd075d",
  "url":"https://download.havoc-os.com/NB1/Havoc-OS-v4.6-20210702-NB1-Official.zip",
  "group":"https://t.me/havoc_NB1"
}
