{
  "oem":"Motorola",
  "name":"Motorola Moto G7 Power",
  "codename":"ocean",
  "filename":"Havoc-OS-v4.15-20220328-ocean-Official.zip",
  "version":"4.15",
  "romtype":"Official",
  "variant":"Vanilla",
  "maintainer":"Andrew Hexen",
  "username":"SyberHexen",
  "size":662626873,
  "datetime":1648427776,
  "filehash":"dacbdc3b49d1f9e0f32c8dd2a4cf5f41",
  "id":"41916e3a7ccde83aed1ec34bc4afc3472b99303dacc1ef5a9cf38ca94cc3735e",
  "url":"https://download.havoc-os.com/ocean/Havoc-OS-v4.15-20220328-ocean-Official.zip",
  "group":"https://t.me/+Oc1flk8GNpAyZWQ1"
}
