{
"oem":"Xiaomi",
"name":"Redmi Note 6 Pro",
"codename":"tulip",
"filename":"Havoc-OS-v4.9-20210929-tulip-Official.zip",
"version":"4.9",
"romtype":"Official",
"variant":"Vanilla",
"maintainer":"Akhil MS",
"username":"AkhilMsAchu",
"size":839780326,
"datetime":1632909022,
"filehash":"ae764cf4664f7a5a8223860ebe47c7ef",
"id":"bdc48186b232a0a61daa3e3fb470b57431bf81112c38b9e5da6151faed7b1a17",
"url":"https://download.havoc-os.com/tulip/Havoc-OS-v4.9-20210929-tulip-Official.zip",
"group":"https://t.me/havoc_tulip"
}
