{
  "oem":"Xiaomi",
  "name":"Xiaomi Redmi Note 7 Pro",
  "codename":"violet",
  "filename":"Havoc-OS-v4.13-20220131-violet-Official.zip",
  "version":"4.13",
  "romtype":"Official",
  "variant":"Vanilla",
  "maintainer":"Athul Dinesan",
  "username":"athuld",
  "size":969609891,
  "datetime":1643615871,
  "filehash":"7101b9321243a14658514cfde201f683",
  "id":"93b3c0778a9c39e068f4d0a4f67f9fbccbf1dd4c81e198f59738306e2469927c",
  "url":"https://download.havoc-os.com/violet/Havoc-OS-v4.13-20220131-violet-Official.zip",
  "group":"https://t.me/+r2lq1BYhIdM5ZDY1"
}
