{
  "oem":"asus",
  "name":"Asus Max Pro M2",
  "codename":"X01BD",
  "filename":"Havoc-OS-v4.9-20211002-X01BD-Official.zip",
  "version":"4.9",
  "romtype":"Official",
  "variant":"Vanilla",
  "maintainer":"Sukeerat SG",
  "username":"irongfly",
  "size":855571971,
  "datetime":1633172546,
  "filehash":"c59dce932d60dc122ad808140ad62586",
  "id":"e23eaa25c86806472e8eb9cdbf0aeab44373603537862f2906b00ddbd4e0763c",
  "url":"https://download.havoc-os.com/X01BD/Havoc-OS-v4.9-20211002-X01BD-Official.zip",
  "group":"https://t.me/havoc_X01BD"
}
