{
  "oem":"Xiaomi",
  "name":"Xiaomi Poco F1",
  "codename":"beryllium",
  "filename":"Havoc-OS-v4.11-20211115-beryllium-Official-GApps.zip",
  "version":"4.11",
  "romtype":"Official",
  "variant":"GApps",
  "maintainer":"Havoc CI",
  "username":"Reignz",
  "size":1476235227,
  "datetime":1636937777,
  "filehash":"bcf96a10dc6d7ea50ebb88c8666abda6",
  "id":"29383f8b7140cbd5039f0635690b90ba8d62def198cde0251d949a31740a2116",
  "url":"https://download.havoc-os.com/beryllium/Havoc-OS-v4.11-20211115-beryllium-Official-GApps.zip",
  "group":"https://t.me/havoc_beryllium"
}
