{
  "oem":"Xiaomi",
  "name":"Xiaomi Mi A2 Lite",
  "codename":"daisy",
  "filename":"Havoc-OS-v4.12-20211221-daisy-Official-GApps.zip",
  "version":"4.12",
  "romtype":"Official",
  "variant":"GApps",
  "maintainer":"LuPe",
  "username":"lupesoltec",
  "size":1167641197,
  "datetime":1640118200,
  "filehash":"b4a4f3a9541e262713ebdda924f23315",
  "id":"b55f2055ba2472319e4cbad94550a1b79af0e48a00f21fea94ac79abc32ca07a",
  "url":"https://download.havoc-os.com/daisy/Havoc-OS-v4.12-20211221-daisy-Official-GApps.zip",
  "group":"https://t.me/havoc_daisy"
}
