{
  "response": [
    {
      "oem": "OnePlus",
      "name": "OnePlus 7 Pro",
      "codename": "guacamole",
      "filename": "Havoc-OS-v3.9-20200927-guacamole-Official-GApps.zip",
      "version": "3.9",
      "romtype": "Official",
      "variant": "GApps",
      "maintainer": "Anushek Prasal (SKULSHADY)",
      "size": "1507243832",
      "datetime": 1601202600,
      "id": "a7847dc3877934f7164e13d51f747687ccbf19d22967f3f809f141fe742af6e9",
      "url": "https://sourceforge.net/projects/havoc-os/files/guacamole/Havoc-OS-v3.9-20200927-guacamole-Official-GApps.zip/download",
      "group": "https://t.me/havoc_oneplus7",
      "changelog": ""
    }
  ]
}
