{
  "oem":"asus",
  "name":"ASUS_I002D",
  "codename":"I002D",
  "filename":"Havoc-OS-v4.8-20210901-I002D-Official-GApps.zip",
  "version":"4.8",
  "romtype":"Official",
  "variant":"GApps",
  "maintainer":"ComicoX",
  "size":1235854802,
  "datetime":1630476329,
  "filehash":"13d013e88723d52d639e39d5dea0183d",
  "id":"5938d4335c4f733e88b0186a96ecf8a77577e94ed3195cfe8d29b1d0620c2b85",
  "url":"https://download.havoc-os.com/I002D/Havoc-OS-v4.8-20210901-I002D-Official-GApps.zip",
  "group":"https://t.me/havoc_i002d"
}
