{
  "oem":"motorola",
  "name":"sanders",
  "codename":"sanders",
  "filename":"Havoc-OS-v4.6-20210618-sanders-Official-GApps.zip",
  "version":"4.6",
  "romtype":"Official",
  "variant":"GApps",
  "maintainer":"P Mahapatra (Ronax)",
  "size":1332374400,
  "datetime":1624042580,
  "filehash":"b4e586d096da39a8dcd8e11623b7263b",
  "id":"e56b6ad16a12bcfc4f2af3ac891cb066015486c3156eea9ee12c592db0e63567",
  "url":"https://download.havoc-os.com/sanders/Havoc-OS-v4.6-20210618-sanders-Official-GApps.zip",
  "group":"https://t.me/havoc_sanders"
}
