{
  "oem":"Xiaomi",
  "name":"Redmi Note 7 Pro",
  "codename":"violet",
  "filename":"Havoc-OS-v4.8-20210812-violet-Official-GApps.zip",
  "version":"4.8",
  "romtype":"Official",
  "variant":"GApps",
  "maintainer":"Athul Dinesan(Logan)",
  "size":1471861634,
  "datetime":1628763515,
  "filehash":"4489c3cfc0f0ea30b735c7e7ef469e5d",
  "id":"ae876a5bcb83afd97b71e08a1c7c1a123d2bf83b8e14df65b2c9f64dc21b60c8",
  "url":"https://download.havoc-os.com/violet/Havoc-OS-v4.8-20210812-violet-Official-GApps.zip",
  "group":"https://t.me/havoc_violet"
}
