{
  "oem":"Google",
  "name":"Pixel 2",
  "codename":"walleye",
  "filename":"Havoc-OS-v4.8-20210810-walleye-Official-GApps.zip",
  "version":"4.8",
  "romtype":"Official",
  "variant":"GApps",
  "maintainer":"Saurabh Jarial (bravesoul349)",
  "size":1140790007,
  "datetime":1628602393,
  "filehash":"cc17285e541aee862751dff73e843644",
  "id":"fa4fefde25fe151a96b22c266662467685513677f9f2850b6064796aaee928cd",
  "url":"https://download.havoc-os.com/walleye/Havoc-OS-v4.8-20210810-walleye-Official-GApps.zip",
  "group":"https://t.me/havoc_pixel2"
}
