{
  "oem":"asus",
  "name":"Asus Zenfone Max Pro M2",
  "codename":"X01BD",
  "filename":"Havoc-OS-v4.14-20220224-X01BD-Official-GApps.zip",
  "version":"4.14",
  "romtype":"Official",
  "variant":"GApps",
  "maintainer":"Sukeerat Singh Goindi",
  "username":"Irongfly",
  "size":1367332891,
  "datetime":1645695519,
  "filehash":"e2d0154ff5b1e47ffd448ff3d3d5ee64",
  "id":"fef9bf62d566868a6de1a6acce74df262830ced2aaad86c64f4e6052865689a8",
  "url":"https://download.havoc-os.com/X01BD/Havoc-OS-v4.14-20220224-X01BD-Official-GApps.zip",
  "group":"https://t.me/+BaJnedaBMMQxNzg9"
}
